validate_models/__init__.py
validate_models/validate_models.py
validate_models-0.0.1.dist-info/LICENSE.txt
validate_models-0.0.1.dist-info/METADATA
validate_models-0.0.1.dist-info/WHEEL
validate_models-0.0.1.dist-info/top_level.txt
validate_models-0.0.1.dist-info/RECORD
